anime.rank-0.1.8.dist-info/DESCRIPTION.rst
anime.rank-0.1.8.dist-info/METADATA
anime.rank-0.1.8.dist-info/RECORD
anime.rank-0.1.8.dist-info/WHEEL
anime.rank-0.1.8.dist-info/entry_points.txt
anime.rank-0.1.8.dist-info/metadata.json
anime.rank-0.1.8.dist-info/top_level.txt
anime.rank-0.1.8.dist-info/zip-safe
src/__init__.py
src/__main__.py
src/sites/__init__.py
src/sites/baidu.py
src/sites/bangumi.py
src/utils/__init__.py
src/utils/common.py
