Metadata-Version: 2.0
Name: anime.rank
Version: 0.1.8
Summary: anime rank
Home-page: https://github.com/csi0n/AnimeRank
Author: csi0n
Author-email: chqssqll@gmail.com
License: MIT
Keywords: python anime rank
Platform: UNKNOWN
Requires-Dist: requests-html
Requires-Dist: click
